opentelemetry/propagators/ot_trace/__init__.py
opentelemetry/propagators/ot_trace/version.py
opentelemetry_propagator_ot_trace-0.60b1.dist-info/METADATA
opentelemetry_propagator_ot_trace-0.60b1.dist-info/WHEEL
opentelemetry_propagator_ot_trace-0.60b1.dist-info/entry_points.txt
opentelemetry_propagator_ot_trace-0.60b1.dist-info/RECORD
